[
    {
        "id":0,
        "nombre": "Fran",
        "edad": 19,
        "user":"fr19"
    },

    {
        "id":1,
        "nombre": "Juan",
        "edad": 20,
        "user": "ju20"
    },

    {
        "id":2,
        "nombre": "Pedro",
        "edad": 21,
        "user": "pe21"
    },
    {
        "id":3,
        "nombre": "Juan",
        "edad": 22,
        "user": "ju22"
    },
    {
        "id":4,
        "nombre": "Pedro",
        "edad": 23,
        "user": "pe23"
    },
    {
        "id":5,
        "nombre": "Juan",
        "edad": 24,
        "user": "ju24"
    },
    {
        "id":6,
        "nombre": "Pedro",
        "edad": 25,
        "user": "pe25"
    },
    {
        "id":7,
        "nombre": "Juan",
        "edad": 26,
        "user": "ju26"
    },
    {
        "id":8,
        "nombre": "Pedro",
        "edad": 27,
        "user": "pe27"
    },
    {
        "id":9,
        "nombre": "Juan",   
        "edad": 28,
        "user": "ju28"
    },
    {
        "id":10,
        "nombre": "Pedro",
        "edad": 29,
        "user": "pe29"
    }
    
]